rer.block.iframembed-1.0.4-py3.10-nspkg.pth
rer/block/iframembed/__init__.py
rer/block/iframembed/configure.zcml
rer/block/iframembed/permissions.zcml
rer/block/iframembed/setuphandlers.py
rer/block/iframembed/testing.py
rer/block/iframembed/browser/__init__.py
rer/block/iframembed/browser/configure.zcml
rer/block/iframembed/browser/controlpanel.py
rer/block/iframembed/browser/overrides/.gitkeep
rer/block/iframembed/browser/static/.gitkeep
rer/block/iframembed/interfaces/__init__.py
rer/block/iframembed/interfaces/layer.py
rer/block/iframembed/interfaces/settings.py
rer/block/iframembed/locales/README.rst
rer/block/iframembed/locales/__init__.py
rer/block/iframembed/locales/rer.block.iframembed.pot
rer/block/iframembed/locales/update.py
rer/block/iframembed/locales/update.sh
rer/block/iframembed/locales/en/LC_MESSAGES/rer.block.iframembed.mo
rer/block/iframembed/locales/en/LC_MESSAGES/rer.block.iframembed.po
rer/block/iframembed/locales/it/LC_MESSAGES/rer.block.iframembed.mo
rer/block/iframembed/locales/it/LC_MESSAGES/rer.block.iframembed.po
rer/block/iframembed/profiles/default/browserlayer.xml
rer/block/iframembed/profiles/default/catalog.xml
rer/block/iframembed/profiles/default/controlpanel.xml
rer/block/iframembed/profiles/default/metadata.xml
rer/block/iframembed/profiles/default/rolemap.xml
rer/block/iframembed/profiles/default/registry/main.xml
rer/block/iframembed/profiles/uninstall/browserlayer.xml
rer/block/iframembed/restapi/__init__.py
rer/block/iframembed/restapi/configure.zcml
rer/block/iframembed/restapi/deserializers/__init__.py
rer/block/iframembed/restapi/deserializers/blocks.py
rer/block/iframembed/restapi/deserializers/configure.zcml
rer/block/iframembed/restapi/services/__init__.py
rer/block/iframembed/restapi/services/configure.zcml
rer/block/iframembed/restapi/services/controlpanel/__init__.py
rer/block/iframembed/restapi/services/controlpanel/adapters.py
rer/block/iframembed/restapi/services/controlpanel/configure.zcml
rer.block.iframembed-1.0.4.dist-info/LICENSE.GPL
rer.block.iframembed-1.0.4.dist-info/LICENSE.rst
rer.block.iframembed-1.0.4.dist-info/METADATA
rer.block.iframembed-1.0.4.dist-info/WHEEL
rer.block.iframembed-1.0.4.dist-info/entry_points.txt
rer.block.iframembed-1.0.4.dist-info/namespace_packages.txt
rer.block.iframembed-1.0.4.dist-info/top_level.txt
rer.block.iframembed-1.0.4.dist-info/RECORD
